{"statusCode": 200, "body": "{\"transaction_id\": \"d1c5fcec-974b-4209-b3a1-def651f98c91\", \"timestamp\": \"2025-03-27T02:38:31.504907\", \"customer_id\": \"cust_8554\", \"items\": [{\"product_id\": \"p1004\", \"product_name\": \"Backpack\", \"price\": 39.99, \"quantity\": 1}, {\"product_id\": \"p1005\", \"product_name\": \"Hat\", \"price\": 14.99, \"quantity\": 3}], \"total_amount\": 84.96, \"payment_method\": \"apple_pay\", \"shipping_address\": {\"street\": \"431 Main St\", \"city\": \"Chicago\", \"state\": \"IL\", \"zip\": \"55612\"}}"}